setup.py
pyscdl.egg-info/PKG-INFO
pyscdl.egg-info/SOURCES.txt
pyscdl.egg-info/dependency_links.txt
pyscdl.egg-info/entry_points.txt
pyscdl.egg-info/requires.txt
pyscdl.egg-info/top_level.txt
scdl/__init__.py
scdl/client.py
scdl/scdl.py
scdl/utils.py